PdbEditorSupport.py
PdbEditorSupport-0.4.0.dist-info/METADATA
PdbEditorSupport-0.4.0.dist-info/RECORD
PdbEditorSupport-0.4.0.dist-info/WHEEL
PdbEditorSupport-0.4.0.dist-info/top_level.txt
