Metadata-Version: 2.1
Name: PdbEditorSupport
Version: 0.4.0
Summary: Display source code in your editor while debugging with pdb.
Home-page: https://github.com/fschulze/PdbEditorSupport
Author: Florian Schulze
Author-email: mail@florian-schulze.net
License: GPL
Keywords: editor pdb sublimetext textmate
Platform: Mac OS X
Classifier: Development Status :: 4 - Beta
Classifier: Environment :: Console
Classifier: Environment :: MacOS X
Classifier: Intended Audience :: Developers
Classifier: Intended Audience :: System Administrators
Classifier: License :: OSI Approved :: GNU General Public License (GPL)
Classifier: Operating System :: MacOS :: MacOS X
Classifier: Programming Language :: Python
Classifier: Topic :: Software Development :: Debuggers
Classifier: Topic :: Text Editors
